Metadata-Version: 2.1
Name: odoo14-addon-bank_accounts_report
Version: 14.0.1.0.0
Summary: Choose which bank accounts will be displayed on invoice and sale order reports
Home-page: https://www.qubiq.es
Author: QubiQ, Odoo Community Association (OCA)
Author-email: support@odoo-community.org
License: AGPL-3
Classifier: Programming Language :: Python
Classifier: Framework :: Odoo
Classifier: Framework :: Odoo :: 14.0
Classifier: License :: OSI Approved :: GNU Affero General Public License v3
Requires-Python: >=3.6
Requires-Dist: odoo14-addon-account-banking-mandate
Requires-Dist: odoo14-addon-account-payment-mode
Requires-Dist: odoo14-addon-account-payment-sale
Requires-Dist: odoo<14.1dev,>=14.0a
